transnormerllm/__init__.py
transnormerllm-0.0.1.dev0.dist-info/METADATA
transnormerllm-0.0.1.dev0.dist-info/WHEEL
transnormerllm-0.0.1.dev0.dist-info/top_level.txt
transnormerllm-0.0.1.dev0.dist-info/RECORD
